binary_format/__init__.py
binary_format/binary_format.py
binary_format-0.0.2.dist-info/METADATA
binary_format-0.0.2.dist-info/WHEEL
binary_format-0.0.2.dist-info/top_level.txt
binary_format-0.0.2.dist-info/RECORD
